QueryOEM/__init__.py
QueryOEM/cli.py
QueryOEM/converters.py
QueryOEM/dell.py
QueryOEM/errors.py
QueryOEM/output.py
QueryOEM/scrapping.py
QueryOEM/test.py
QueryOEM/conf/__init__.py
QueryOEM-1.0.4.dist-info/DESCRIPTION.rst
QueryOEM-1.0.4.dist-info/METADATA
QueryOEM-1.0.4.dist-info/RECORD
QueryOEM-1.0.4.dist-info/WHEEL
QueryOEM-1.0.4.dist-info/metadata.json
QueryOEM-1.0.4.dist-info/top_level.txt
